cosysairsim/__init__.py
cosysairsim/client.py
cosysairsim/colormap.npy
cosysairsim/pfm.py
cosysairsim/types.py
cosysairsim/utils.py
cosysairsim-3.3.0.dist-info/LICENSE
cosysairsim-3.3.0.dist-info/METADATA
cosysairsim-3.3.0.dist-info/WHEEL
cosysairsim-3.3.0.dist-info/top_level.txt
cosysairsim-3.3.0.dist-info/RECORD
