Metadata-Version: 2.1
Name: cosysairsim
Version: 3.3.0
Summary: This package contains simple Python client for Cosys-AirSim. This integrates most API functions over RPC.
Author-email: Shital Shah <shitals@microsoft.com>, Wouter Jansen <wouter.jansen@uantwerpen.be>
License: MSR Aerial Informatics and Robotics Platform
Project-URL: Repository, https://github.com/Cosys-Lab/Cosys-AirSim
Project-URL: Documentation, https://cosys-lab.github.io/Cosys-AirSim/
Keywords: simulation,airsim,api
Classifier: Development Status :: 6 - Mature
Classifier: Programming Language :: Python
Classifier: Programming Language :: Python :: 3
Classifier: Programming Language :: Python :: 3.7
Classifier: Programming Language :: Python :: 3.8
Classifier: Programming Language :: Python :: 3.9
Classifier: Programming Language :: Python :: 3.10
Classifier: Programming Language :: Python :: 3.11
Classifier: Operating System :: Microsoft :: Windows
Classifier: Operating System :: Unix
Classifier: Topic :: Scientific/Engineering
Classifier: Topic :: Software Development
Requires-Python: >=3.7
License-File: LICENSE
Requires-Dist: numpy
Requires-Dist: rpc-msgpack
